dbx_sql_runner/__init__.py
dbx_sql_runner/api.py
dbx_sql_runner/cli.py
dbx_sql_runner/exceptions.py
dbx_sql_runner/linter.py
dbx_sql_runner/models.py
dbx_sql_runner/project.py
dbx_sql_runner/runner.py
dbx_sql_runner/scaffold.py
dbx_sql_runner/adapters/base.py
dbx_sql_runner/adapters/databricks.py
dbx_sql_runner-0.2.2.dist-info/licenses/LICENCE.txt
dbx_sql_runner-0.2.2.dist-info/METADATA
dbx_sql_runner-0.2.2.dist-info/WHEEL
dbx_sql_runner-0.2.2.dist-info/entry_points.txt
dbx_sql_runner-0.2.2.dist-info/top_level.txt
dbx_sql_runner-0.2.2.dist-info/RECORD
