Metadata-Version: 2.4
Name: dbx-sql-runner
Version: 0.2.2
Summary: A lightweight SQL transformation tool for Databricks SQL
Author-email: Sharma <munish7771@gmail.com>
Project-URL: Homepage, https://github.com/munish7771/dbx-sql-runner
Project-URL: Documentation, https://munish7771.github.io/dbx-sql-runner/
Classifier: Programming Language :: Python :: 3
Classifier: License :: OSI Approved :: MIT License
Classifier: Operating System :: OS Independent
Requires-Python: >=3.8
License-File: LICENCE.txt
Requires-Dist: networkx>=3.0
Requires-Dist: databricks-sql-connector[pyarrow]>=3.0
Requires-Dist: PyYAML>=6.0
Requires-Dist: sqlglot>=11.0
Provides-Extra: dev
Requires-Dist: pytest; extra == "dev"
Requires-Dist: ruff; extra == "dev"
Dynamic: license-file
